pypi_chat_server-0.0.2.dist-info/METADATA
pypi_chat_server-0.0.2.dist-info/RECORD
pypi_chat_server-0.0.2.dist-info/WHEEL
pypi_chat_server-0.0.2.dist-info/entry_points.txt
pypi_chat_server-0.0.2.dist-info/top_level.txt
pypi_server/__init__.py
pypi_server/main.py
pypi_server/test_server.py
pypi_server/core/__init__.py
pypi_server/core/handler.py
pypi_server/core/server.py
pypi_server/db/__init__.py
pypi_server/db/managers.py
pypi_server/db/models.py
pypi_server/db/settings.py
pypi_server/protocol/__init__.py
pypi_server/protocol/jim.py
pypi_server/protocol/msg_handler.py
pypi_server/utils/__init__.py
pypi_server/utils/decorators.py
pypi_server/utils/log_config.py
pypi_server/utils/utils.py
